oceanbase_sqlalchemy/__init__.py
oceanbase_sqlalchemy/cx_oceanbase.py
oceanbase_sqlalchemy/cx_oracle.py
oceanbase_sqlalchemy/requirements.py
oceanbase_sqlalchemy/utils.py
oceanbase_sqlalchemy-0.5.1.dist-info/licenses/LICENSE
test/__init__.py
test/conftest.py
test/test_basic.py
test/test_optimization.py
test/test_suite.py
oceanbase_sqlalchemy-0.5.1.dist-info/METADATA
oceanbase_sqlalchemy-0.5.1.dist-info/WHEEL
oceanbase_sqlalchemy-0.5.1.dist-info/entry_points.txt
oceanbase_sqlalchemy-0.5.1.dist-info/top_level.txt
oceanbase_sqlalchemy-0.5.1.dist-info/RECORD
