Metadata-Version: 2.4
Name: oceanbase-sqlalchemy
Version: 0.5.1
Summary: SQLAlchemy dialect for OceanBase Oracle mode (supports SQLAlchemy 1.3.x and 2.0+)
Home-page: https://github.com/oceanbase/ecology-plugins
Author: OceanBase Team
Author-email: support@oceanbase.com
Project-URL: Bug Reports, https://github.com/oceanbase/ecology-plugins/issues
Project-URL: Source, https://github.com/oceanbase/ecology-plugins
Project-URL: Documentation, https://github.com/oceanbase/ecology-plugins#readme
Keywords: sqlalchemy oceanbase oracle dialect database
Classifier: Development Status :: 4 - Beta
Classifier: Intended Audience :: Developers
Classifier: License :: OSI Approved :: Apache Software License
Classifier: Operating System :: OS Independent
Classifier: Programming Language :: Python :: 3
Classifier: Programming Language :: Python :: 3.7
Classifier: Programming Language :: Python :: 3.8
Classifier: Programming Language :: Python :: 3.9
Classifier: Programming Language :: Python :: 3.10
Classifier: Programming Language :: Python :: 3.11
Classifier: Programming Language :: Python :: 3.12
Classifier: Topic :: Database
Classifier: Topic :: Software Development :: Libraries :: Python Modules
Requires-Python: >=3.7
License-File: LICENSE
Requires-Dist: sqlalchemy>=1.3.0
Requires-Dist: cx_oracle>=8.0.0
Dynamic: author
Dynamic: author-email
Dynamic: classifier
Dynamic: description
Dynamic: description-content-type
Dynamic: home-page
Dynamic: keywords
Dynamic: license-file
Dynamic: project-url
Dynamic: requires-dist
Dynamic: requires-python
Dynamic: summary
